gdoctableapppy/__init__.py
gdoctableapppy/gdoctableapp.py
tests/__init__.py
tests/test_gdoctableapppy.py
tests/test_getfilelist.py
gdoctableapppy-1.1.0.dist-info/LICENCE
gdoctableapppy-1.1.0.dist-info/METADATA
gdoctableapppy-1.1.0.dist-info/WHEEL
gdoctableapppy-1.1.0.dist-info/top_level.txt
gdoctableapppy-1.1.0.dist-info/RECORD
