Metadata-Version: 2.1
Name: gdoctableapppy
Version: 1.1.0
Summary: This is a python library to manage the tables on Google Document using Google Docs API.
Home-page: https://github.com/tanaikech/gdoctableapppy
Author: Kanshi TANAIKE
Author-email: tanaike@hotmail.com
License: MIT License
Keywords: google document,google docs,docs api,table,manager,developer tools
Platform: UNKNOWN
Classifier: Development Status :: 5 - Production/Stable
Classifier: Intended Audience :: Developers
Classifier: License :: OSI Approved :: MIT License
Classifier: Natural Language :: English
Classifier: Programming Language :: Python :: 3.5
Requires-Dist: google-api-python-client
